{
  "AppId": "ComponentManager",
  "LatestVersion": "4.4.7",
  "RuntimeVersion": "4.4.7",
  "Mandatory": false,
  "PackageKind": "FullInstallAndLoaderUpdate",
  "IncludesLoader": true,
  "RequiresLoaderUpdate": true,
  "RequiresInventorRestart": true,
  "InstallerExeName": "ComponentManager.Installer.exe",
  "InstallerArguments": "--apply-update",
  "ZipUrl": "https://raw.githubusercontent.com/vince3dse/COMPONENT_MANAGER_UPDATE/main/releases/ComponentManager_4.4.7.zip",
  "Checksum": "92C3EFB6E9DDD19C532C0903182F3EFB7A3BC75271505CD48B076DE20FDE4EE1",
  "Notes": "Release 4.4.7"
}